<annotation>
	<folder>train</folder>
	<filename>493.jpg</filename>
	<path>/Users/bo/Desktop/pothole_image/Tensorflow/workspace/images/train/493.jpg</path>
	<source>
		<database>Unknown</database>
	</source>
	<size>
		<width>2592</width>
		<height>1944</height>
		<depth>3</depth>
	</size>
	<segmented>0</segmented>
	<object>
		<name>damage</name>
		<pose>Unspecified</pose>
		<truncated>0</truncated>
		<difficult>0</difficult>
		<bndbox>
			<xmin>798</xmin>
			<ymin>962</ymin>
			<xmax>1898</xmax>
			<ymax>1457</ymax>
		</bndbox>
	</object>
	<object>
		<name>damage</name>
		<pose>Unspecified</pose>
		<truncated>0</truncated>
		<difficult>0</difficult>
		<bndbox>
			<xmin>1208</xmin>
			<ymin>1292</ymin>
			<xmax>2298</xmax>
			<ymax>1757</ymax>
		</bndbox>
	</object>
	<object>
		<name>crack</name>
		<pose>Unspecified</pose>
		<truncated>0</truncated>
		<difficult>0</difficult>
		<bndbox>
			<xmin>1638</xmin>
			<ymin>1632</ymin>
			<xmax>2583</xmax>
			<ymax>1932</ymax>
		</bndbox>
	</object>
</annotation>
