<annotation>
	<folder>train</folder>
	<filename>90.jpg</filename>
	<path>/Users/bo/Desktop/pothole_image/Tensorflow/workspace/images/train/90.jpg</path>
	<source>
		<database>Unknown</database>
	</source>
	<size>
		<width>436</width>
		<height>269</height>
		<depth>3</depth>
	</size>
	<segmented>0</segmented>
	<object>
		<name>pothole</name>
		<pose>Unspecified</pose>
		<truncated>0</truncated>
		<difficult>0</difficult>
		<bndbox>
			<xmin>194</xmin>
			<ymin>42</ymin>
			<xmax>340</xmax>
			<ymax>177</ymax>
		</bndbox>
	</object>
	<object>
		<name>pothole</name>
		<pose>Unspecified</pose>
		<truncated>0</truncated>
		<difficult>0</difficult>
		<bndbox>
			<xmin>21</xmin>
			<ymin>60</ymin>
			<xmax>236</xmax>
			<ymax>106</ymax>
		</bndbox>
	</object>
</annotation>
